mathparse/__init__.py
mathparse/mathparse.py
mathparse/mathwords.py
mathparse-0.2.5.dist-info/licenses/LICENSE
mathparse-0.2.5.dist-info/METADATA
mathparse-0.2.5.dist-info/WHEEL
mathparse-0.2.5.dist-info/top_level.txt
mathparse-0.2.5.dist-info/RECORD
