Metadata-Version: 2.4
Name: mathparse
Version: 0.2.5
Summary: mathparse is a library for solving mathematical equations contained in strings
Author: Gunther Cox
License-Expression: MIT
Project-URL: Documentation, https://mathparse.chatterbot.us
Project-URL: Repository, https://github.com/gunthercox/mathparse
Project-URL: Changelog, https://github.com/gunthercox/mathparse/releases
Keywords: mathparse,mathematics,math,nlp
Classifier: Development Status :: 4 - Beta
Classifier: Intended Audience :: Developers
Classifier: Operating System :: OS Independent
Classifier: Topic :: Software Development :: Libraries :: Python Modules
Classifier: Topic :: Scientific/Engineering :: Mathematics
Classifier: Topic :: Text Processing :: General
Classifier: Topic :: Text Processing :: Linguistic
Classifier: Programming Language :: Python
Requires-Python: <3.14,>=3.9
License-File: LICENSE
Provides-Extra: test
Requires-Dist: flake8; extra == "test"
Requires-Dist: sphinx<9.0,>=7.4; extra == "test"
Dynamic: license-file
